[{"name":"start_processing.action_controller","payload":{"controller":"PaintingsController","action":"index","params":{"action":"index","controller":"paintings"},"format":"html","method":"GET","path":"/paintings"},"time":"2013-07-15T20:15:43-04:00","transaction_id":"d2d80f32d28d3e01c41d","end":"2013-07-15T20:15:43-04:00","duration":0.003},{"name":"sql.active_record","payload":{"sql":"SELECT \"paintings\".* FROM \"paintings\" ","name":"Painting Load","connection_id":70118845578860},"time":"2013-07-15T20:15:43-04:00","transaction_id":"d2d80f32d28d3e01c41d","end":"2013-07-15T20:15:43-04:00","duration":0.434},{"name":"!render_template.action_view","payload":{"virtual_path":"shared/_list"},"time":"2013-07-15T20:15:43-04:00","transaction_id":"d2d80f32d28d3e01c41d","end":"2013-07-15T20:15:43-04:00","duration":16.195999999999998},{"name":"render_partial.action_view","payload":{"identifier":"/Users/Sean/Documents/projects/david_loncle/port/app/views/shared/_list.html.haml"},"time":"2013-07-15T20:15:43-04:00","transaction_id":"d2d80f32d28d3e01c41d","end":"2013-07-15T20:15:43-04:00","duration":16.246},{"name":"!render_template.action_view","payload":{"virtual_path":"paintings/index"},"time":"2013-07-15T20:15:43-04:00","transaction_id":"d2d80f32d28d3e01c41d","end":"2013-07-15T20:15:43-04:00","duration":17.125},{"name":"render_template.action_view","payload":{"identifier":"/Users/Sean/Documents/projects/david_loncle/port/app/views/paintings/index.html.haml","layout":"layouts/application"},"time":"2013-07-15T20:15:43-04:00","transaction_id":"d2d80f32d28d3e01c41d","end":"2013-07-15T20:15:43-04:00","duration":17.145},{"name":"!render_template.action_view","payload":{"virtual_path":"layouts/application"},"time":"2013-07-15T20:15:43-04:00","transaction_id":"d2d80f32d28d3e01c41d","end":"2013-07-15T20:15:43-04:00","duration":158.588},{"name":"process_action.action_controller","payload":{"controller":"PaintingsController","action":"index","params":{"action":"index","controller":"paintings"},"format":"html","method":"GET","path":"/paintings","status":200,"view_runtime":177.361,"db_runtime":0.434},"time":"2013-07-15T20:15:43-04:00","transaction_id":"d2d80f32d28d3e01c41d","end":"2013-07-15T20:15:43-04:00","duration":179.208}]